{
  "kind": "singleType",
  "collectionName": "issues",
  "info": {
    "singularName": "issue",
    "pluralName": "issues",
    "displayName": "Issue",
    "description": ""
  },
  "options": {
    "draftAndPublish": true
  },
  "pluginOptions": {
    "i18n": {
      "localized": true
    }
  },
  "attributes": {
    "Issues": {
      "type": "component",
      "repeatable": true,
      "component": "issue.issue",
      "pluginOptions": {
        "i18n": {
          "localized": true
        }
      }
    }
  }
}
